yakutils/__init__.py
yakutils/_csv.py
yakutils/_datetime.py
yakutils/_functools.py
yakutils/_hashlib.py
yakutils/_json.py
yakutils/_logging.py
yakutils/_random.py
yakutils/_urllib.py
yakutils-2.0.0.dist-info/LICENSE
yakutils-2.0.0.dist-info/METADATA
yakutils-2.0.0.dist-info/WHEEL
yakutils-2.0.0.dist-info/top_level.txt
yakutils-2.0.0.dist-info/zip-safe
yakutils-2.0.0.dist-info/RECORD
