Metadata-Version: 2.1
Name: yakutils
Version: 2.0.0
Summary: A really lazy package
Home-page: https://github.com/nficano/yakutils
Author: Nick Ficano
Author-email: nficano@gmail.com
License: The Unlicense
Platform: UNKNOWN
Classifier: License :: OSI Approved :: The Unlicense (Unlicense)
Classifier: Programming Language :: Python
Classifier: Programming Language :: Python :: Implementation :: CPython
Classifier: Programming Language :: Python :: Implementation :: PyPy
License-File: LICENSE
